ranlibx/__init__.py
ranlibx/authentication.py
ranlibx/constants.py
ranlibx/flow.py
ranlibx/server.py
ranlibx/state.py
ranlibx/_external/install_checks.py
ranlibx/api/__init__.py
ranlibx/api/auth.py
ranlibx/api/main.py
ranlibx/api/schemas/__init__.py
ranlibx/api/schemas/token.py
ranlibx/cli/__init__.py
ranlibx/cli/main.py
ranlibx/cli/subcmds/__init__.py
ranlibx/cli/subcmds/install.py
ranlibx-0.1.4.dist-info/METADATA
ranlibx-0.1.4.dist-info/WHEEL
ranlibx-0.1.4.dist-info/entry_points.txt
ranlibx-0.1.4.dist-info/licenses/LICENSE
ranlibx-0.1.4.dist-info/RECORD
