Metadata-Version: 2.3
Name: ranlibx
Version: 0.1.4
Summary: Global interface for RAN
Project-URL: Repository, https://github.com/ran-labs/ranlibx
Project-URL: Changelog, https://github.com/ran-labs/ranlibx/blob/main/CHANGELOG.md
Project-URL: Homepage, https://ran.so
Project-URL: Documentation, https://ran.so/docs
Project-URL: Source, https://github.com/ran-labs/ranlibx
Project-URL: Tracker, https://github.com/ran-labs/ranlibx/issues
Project-URL: Twitter, https://twitter.com/RANdotSO
Author-email: Ameer Arsala <ameer.arsala03@gmail.com>
License:                                  Apache License
License-File: LICENSE
Requires-Python: >=3.9
Requires-Dist: email-validator<3,>=2.2.0
Requires-Dist: fastapi<0.113,>=0.112.2
Requires-Dist: httpx<0.28,>=0.27.2
Requires-Dist: pydantic>2.0
Requires-Dist: rich<14,>=13.8.1
Requires-Dist: typer<0.13,>=0.12.5
Requires-Dist: uvicorn[standard]<0.31,>=0.30.6
Provides-Extra: fdev
Requires-Dist: hatch<2,>=1.12.0; extra == 'fdev'
Requires-Dist: pytest; extra == 'fdev'
Requires-Dist: tomli; extra == 'fdev'
